{
  "api": {
    "_requestlogger": {
      "logbody": [
        "application/json"
      ],
      "logurl": true,
      "printbody": false
    },
    "_responselogger": {
      "logbody": [
        "application/json"
      ],
      "logurl": false,
      "printbody": false
    },
    "areacollision": {
      "selecteddayslimit": 31,
      "sensorcountlimit": 500,
      "usertasklimit": 10
    },
    "capturedface": {
      "rankfeaturecandidatesfactor": 5,
      "repositoryname": "ReverseSort+SkipCount",
      "tablename": "faces"
    },
    "capturequery": {
      "cpu_num": 1,
      "index_query": 100,
      "sensor_query": 60,
      "sensor_resource": 60,
      "single_goroutine_query": 50
    },
    "civil": {
      "rankfeaturecandidatesfactor": 15,
      "repositoryname": "ReverseSort+SkipCount"
    },
    "dayinnightout": {
      "selecteddayslimit": 31,
      "sensorcountlimit": 500,
      "usertasklimit": 10
    },
    "export": {
      "civilimagecount": 3,
      "downloadassetconcurrency": 100,
      "faceeventcolumns": [
        "序号",
        "抓拍人脸图片",
        "比中人脸图片",
        "比对分数",
        "抓拍时间",
        "监控点名称",
        "比对库名称",
        "姓名",
        "证件号",
        "备注",
        "审核状态",
        "审核人",
        "全景图"
      ],
      "failedcivilimagecount": 3,
      "personfilecolumns": [
        "序号",
        "姓名",
        "身份证号",
        "档案标志照片",
        "档案建立时间",
        "实名状态",
        "关注状态",
        "分值"
      ]
    },
    "faceevent": {
      "repositoryname": "ReverseSort+SkipCount"
    },
    "facewhiteevent": {
      "rankfeaturecandidatesfactor": 5,
      "repositoryname": "ReverseSort+SkipCount",
      "tablename": "white_warn"
    },
    "fakeplate": {
      "selecteddayslimit": 90,
      "sensorcountlimit": 500,
      "usertasklimit": 10
    },
    "firstappearance": {
      "backtrackingdayslimit": 90,
      "selecteddayslimit": 90,
      "sensorcountlimit": 500,
      "usertasklimit": 10
    },
    "frequencyanalyze": {
      "common": {
        "createtaskmaxsensorcount": 500,
        "createtaskmaxtsdurationdays": 31,
        "maxtasknuminathena": 10,
        "maxtasknumofoneuser": 10
      }
    },
    "hidden": {
      "selecteddayslimit": 31,
      "sensorcountlimit": 500,
      "usertasklimit": 10
    },
    "logout": {
      "updatesecuritytoken": false
    },
    "org": {
      "max_org_level": 6,
      "max_org_num_per_level": 500
    },
    "pathanalyze": {
      "selecteddayslimit": 31,
      "sensorcountlimit": 500,
      "usertasklimit": 10
    },
    "personfile": {
      "repositoryname": "ReverseSort+SkipCount",
      "searchfeature": 0.88
    },
    "preview": {
      "cacheexpiretimeoflatestts": 70,
      "maxkeepalivetime": "60s",
      "schedulertime": "5s"
    },
    "record": {
      "cachethreshold": 1,
      "nginxport": "80"
    },
    "repocollision": {
      "maxconfidence": 1,
      "maxrepocount": 5,
      "minconfidence": 0.8,
      "minrepocount": 2,
      "usertasklimit": 10
    },
    "repostatistics": {
      "repoidcount": 3,
      "repoids": [
        "0002",
        "adf92850-87fc-4226-be36-0aa2ee44c82d",
        "4b273149-a4b6-4a51-b79c-f5b8f0707d89"
      ]
    },
    "templatesbasepath": "/home/{{ansible_user}}/platformTG/loki/latest/config/templates",
    "updatedevicerole": {
      "updatesecuritytoken": true
    },
    "updatefuncrole": {
      "updatesecuritytoken": true
    },
    "updatepassword": {
      "updatesecuritytoken": true
    },
    "updateuser": {
      "updatesecuritytoken": true
    },
    "vehiclefile": {
      "repositoryname": "ReverseSort+SkipCount"
    }
  },
  "auth": {
    "impersonateallowlist": [
      ".*"
    ],
    "key": "4rd5rAPPz52dhvjlSK1lTT08dOVNxFKN0GeosDeps3cAUwlL5YzkGBDbD3sGvogd",
    "maxrefresh": "168h",
    "timeout": "168h"
  },
  "cronjob": {
    "capture_count": {
      "cronscript": "0 25 0 * * *",
      "forward_days": 0
    },
    "civil_count": {
      "cronscript": "@hourly"
    },
    "delete_task": {
      "cronscript": "0 45 22 * * *"
    },
    "file_count": {
      "cronscript": "0 30 0 * * *",
      "forward_days": 0
    },
    "impact": {
      "confidence": 0.75,
      "cronscript": "0 19 16 * * *",
      "days": 20,
      "standerrepoid": "0001",
      "timeoutduration": 18000
    },
    "partition": {
      "face_cronscript": "@weekly",
      "sax_cronscript": "0 0 23 1 * *",
      "sax_switcher": false
    },
    "repo": {
      "cronscriptclear": "0 30 23 * * *",
      "cronscriptpiccount": "0 45 23 * * *"
    },
    "vid": {
      "updatecron": "0 * * * * ?",
      "updateseconds": 100
    }
  },
  "database": {
    "connectionstring": "postgres://postgres:Zstvgcs@9102@{{groups.db[0]}}/deepface_v5",
    "connmaxlifetime": "1m",
    "loglevel": "info",
    "maxidleconns": 100,
    "maxopenconns": 100,
    "showsql": false
  },
  "limit": {
    "file_search_tab_bar_default": 8,
    "file_search_tab_bar_repo": 8,
    "sensor": 1000,
    "sensor_tags_capacity": 20,
    "user_capture_favorite": 1000
  },
  "log": {
    "http": true,
    "skip_path": []
  },
  "platform": {
    "consumer": false,
    "defaultgroup": "123",
    "kafkaaddress": [
      "{{groups.kafka[0]}}:{{port}}",
      "{{groups.kafka[0]}}:{{port}}",
      "{{groups.kafka[0]}}:{{port}}"
    ],
    "kafkalogtopic": "user_operation_log",
    "kafkasynctopic": "ferry_topic",
    "kafkatagstopic": "file-message-topic",
    "lokitopic": "loki_sync_topic",
    "needsync": false,
    "noticetopic": "iris-message-topic",
    "producer": false
  },
  "pool": {
    "capacity": 100
  },
  "services": {
    "arcee": {
      "addr": "127.0.0.1:7502",
      "connect_number": 10,
      "try_times": 3
    },
    "archimedes": {
      "addr": "http://{{groups.tg[0]}}:6666/archimedes/v1",
      "faceagevalue": 1,
      "facegendervalue": 16,
      "rate": 10000,
      "timeout_second": 60,
      "vehiclecolorvalue": 39,
      "vehicleplatetypevalue": 20,
      "vehicletypevalue": 34
    },
    "athena": {
      "addr": "http://127.0.0.1:2013",
      "platform_sync": {
        "gb": {
          "url": "http://%s:%d/dgsip/catalog"
        },
        "pvg": {
          "url": "netposa://%s:%s@%s:%d"
        }
      }
    },
    "deepcloud": {
      "access_key": "7966023d-0eee-4104-9c2f-8efa4279442a",
      "addr": "http://{{groups.bigtoe[0]}}:39876/api",
      "authkey": "dp-auth-v0",
      "secret_key": "9e7b1900-302b-4059-bcaa-047262f3ca3b",
      "switch": false,
      "timeout_second": 60
    },
    "elasticsearch": {
      "inuse": false,
      "url": "http://127.0.0.1:9200"
    },
    "fse_black": {
      "addr": "http://{{groups.bigtoe[0]}}:3154/x-api/v1",
      "default_repo": [
        "0001",
        "0002",
        "0003",
        "0004",
        "0005",
        "0006"
      ],
      "face": {
        "capacity": 1000000000,
        "index_type": "int8",
        "level": "ram",
        "options": {
          "hashingnum": "2",
          "rotate": "false",
          "usefeatureidmap": "true"
        },
        "replications": 1
      }
    },
    "fse_runtime": {
      "addr": "http://{{groups.bigtoe[0]}}:3154/x-api/v1",
      "face": {
        "capacity": 50000000,
        "index_type": "int8",
        "level": "ram",
        "options": {
          "hashingnum": "2",
          "rotate": "true",
          "usefeatureidmap": "false"
        },
        "replications": 1,
        "repo_id": "capture-face-repo"
      },
      "nonmotor": {
        "capacity": 7000000,
        "index_type": "int8",
        "level": "ram",
        "options": {
          "hashingnum": "2",
          "rotate": "true",
          "usefeatureidmap": "false"
        },
        "replications": 1,
        "repo_id": "capture-nonmotor-repo"
      },
      "pedestrian": {
        "capacity": 7000000,
        "index_type": "int8",
        "level": "ram",
        "options": {
          "hashingnum": "2",
          "rotate": "true",
          "usefeatureidmap": "false"
        },
        "replications": 1,
        "repo_id": "capture-pedestrian-repo"
      },
      "vehicle": {
        "capacity": 7000000,
        "index_type": "int8",
        "level": "ram",
        "options": {
          "hashingnum": "2",
          "rotate": "true",
          "usefeatureidmap": "false"
        },
        "replications": 1,
        "repo_id": "capture-vehicle-repo"
      }
    },
    "hercules": {
      "addr": "http://127.0.0.1:1315"
    },
    "link": {
      "addr": "http://{{groups.bigtoe[0]}}:30233"
    },
    "megvii": {
      "addr": "http://104.35.96.231:81",
      "needtestdata": true
    },
    "mserver": {
      "out_addr": "{{groups.tg[0]}}:8905",
      "run_addr": "http://{{groups.tg[0]}}:9009"
    },
    "pse": {
      "addr": "http://{{groups.tg[0]}}:1989"
    },
    "redis": {
      "cache": {
        "addr": "{{groups.redis[0]}}:6379",
        "password": "deepglint@2013"
      },
      "store": {
        "addr": "{{groups.redis[0]}}:6379",
        "password": "deepglint@2013"
      }
    },
    "sax": {
      "addr": "http://127.0.0.1:50051"
    },
    "sentry": {
      "dsn": "http://7f524bae4b7f49f5b6f2c6276570f66b@192.168.2.61:9000/2",
      "environment": "2.169",
      "switcher": true
    },
    "themis": {
      "addr": "http://127.0.0.1:7777",
      "timeout_second": 60
    },
    "uias": {
      "addr": "http://127.0.0.1:9090"
    },
    "vse_all": {
      "addr": "http://{{groups.bigtoe[0]}}:38080"
    },
    "vse_face": {
      "addr": "http://{{groups.bigtoe[0]}}:38080"
    },
    "vse_vehicle": {
      "addr": "http://{{groups.bigtoe[0]}}:38080"
    },
    "ymer": {
      "addr": "http://127.0.0.1:9750"
    }
  },
  "similarity": {
    "configtype": 1,
    "cosaparams": [
      1.58730175,
      2.30769028,
      1.08108107,
      0.85106399
    ],
    "cosbparams": [
      -0.26428582,
      -0.74730632,
      0.09108108,
      0.25255307
    ],
    "costhreashold": 0.85,
    "isopen": true,
    "linearalpha": 1,
    "linearbeta": 0,
    "slidingwindowmillsecond": 5000,
    "thresparams": [
      0.6705,
      0.6835,
      0.702
    ],
    "topnum": 5
  },
  "switcher": {
    "person_file_compare": true,
    "repo_collision": false,
    "repo_statistics": false,
    "vid_combine": false
  },
  "tags": {
    "person": {
      "eight": 128,
      "five": 16,
      "four": 8,
      "one": 1,
      "seven": 64,
      "six": 32,
      "three": 4,
      "two": 2
    },
    "vehicle": [
      "one",
      "two",
      "three",
      "four",
      "five",
      "six",
      "seven",
      "eight"
    ]
  }
}
